Workbook

Sheet Instructions
A1: CapEx Asset Register — Instructions
A2: Purpose: Maintain the list of capitalized software projects, their amortization, and net book value.
A3: Cadence: Update monthly after the engineering CapEx report is delivered (1st of each month).
A5: Workflow each month:
A6: 1. Open the latest monthly CapEx report XLSX (delivered via Drive + email).
A7: 2. On the 'Monthly Additions' tab, append one row per project_code with the $ added this month.
A8: 3. On the 'Asset Register' tab, update 'Total Capitalized' for each project (sum of all additions to date).
A9: 4. Set 'In-Service Date' the FIRST month the project delivers production value. Amortization begins then.
A10: 5. 'Monthly Amortization' and 'Net Book Value' are formulas — do not overwrite unless useful life changes.
A11: 6. On 'Journal Entry Helper' copy the month's suggested JE lines to your GL (NetSuite, QBO, etc.).
A12: 7. If a project is retired or impaired, set Status accordingly and zero out future amortization manually.
A14: Conventions:
... A19: Questions? finance@yourcompany.com

Sheet Asset Register
A1: Project Code | B1: Description | C1: In-Service Date | D1: Total Capitalized | E1: Useful Life (months) | F1: Monthly Amortization | G1: Accumulated Amortization | H1: Net Book Value | I1: Status
A2: CAPEX-2026-PLATFORM-SSO | B2: SSO Platform Rollout | C2: 2026-03-15 | D2: 185000 | E2: 36 | F2: =D2/E2 | G2: 0 | H2: =D2-G2 | I2: Active
A3: CAPEX-2026-RESIDENT-APP | B3: Resident App v2 checkout flow | C3: 2026-04-01 | D3: 92500 | E3: 36 | F3: =D3/E3 | G3: 0 | H3: =D3-G3 | I3: Active

Sheet Monthly Additions
A1: Month | B1: Project Code | C1: Amount Added | D1: Source Report File | E1: Notes
A2: 2026-03 | B2: CAPEX-2026-PLATFORM-SSO | C2: 125000 | D2: capex-report-2026-03.xlsx | E2: Initial build
A3: 2026-03 | B3: CAPEX-2026-RESIDENT-APP | C3: 55000 | D3: capex-report-2026-03.xlsx | E3: Scaffolding + payment form
A4: 2026-04 | B4: CAPEX-2026-PLATFORM-SSO | C4: 60000 | D4: capex-report-2026-04.xlsx | E4: Finalize + ship
A5: 2026-04 | B5: CAPEX-2026-RESIDENT-APP | C5: 37500 | D5: capex-report-2026-04.xlsx

Sheet Amortization Schedule
A1: Month # | B1: Period (yyyy-mm) | C1: Project Code | D1: Monthly Amortization | E1: Cumulative Amortization | F1: Remaining NBV
A2: 1 | B2: 2026-03 | C2: CAPEX-2026-PLATFORM-SSO | D2: ='Asset Register'!D2/'Asset Register'!E2 | E2: =D2*A2 | F2: ='Asset Register'!D2-E2
A3: 2 | B3: 2026-04 | C3: CAPEX-2026-PLATFORM-SSO | D3: ='Asset Register'!D2/'Asset Register'!E2 | E3: =D3*A3 | F3: ='Asset Register'!D2-E3
A4: 3 | B4: 2026-05 | C4: CAPEX-2026-PLATFORM-SSO | D4: ='Asset Register'!D2/'Asset Register'!E2 | E4: =D4*A4 | F4: ='Asset Register'!D2-E4
A5: 4 | B5: 2026-06 | C5: CAPEX-2026-PLATFORM-SSO | D5: ='Asset Register'!D2/'Asset Register'!E2 | E5: =D5*A5 | F5: ='Asset Register'!D2-E5
A6: 5 | B6: 2026-07 | C6: CAPEX-2026-PLATFORM-SSO | D6: ='Asset Register'!D2/'Asset Register'!E2 | E6: =D6*A6 | F6: ='Asset Register'!D2-E6
A7: 6 | B7: 2026-08 | C7: CAPEX-2026-PLATFORM-SSO | D7: ='Asset Register'!D2/'Asset Register'!E2 | E7: =D7*A7 | F7: ='Asset Register'!D2-E7
A8: 7 | B8: 2026-09 | C8: CAPEX-2026-PLATFORM-SSO | D8: ='Asset Register'!D2/'Asset Register'!E2 | E8: =D8*A8 | F8: ='Asset Register'!D2-E8
A9: 8 | B9: 2026-10 | C9: CAPEX-2026-PLATFORM-SSO | D9: ='Asset Register'!D2/'Asset Register'!E2 | E9: =D9*A9 | F9: ='Asset Register'!D2-E9
A10: 9 | B10: 2026-11 | C10: CAPEX-2026-PLATFORM-SSO | D10: ='Asset Register'!D2/'Asset Register'!E2 | E10: =D10*A10 | F10: ='Asset Register'!D2-E10
A11: 10 | B11: 2026-12 | C11: CAPEX-2026-PLATFORM-SSO | D11: ='Asset Register'!D2/'Asset Register'!E2 | E11: =D11*A11 | F11: ='Asset Register'!D2-E11
A12: 11 | B12: 2027-01 | C12: CAPEX-2026-PLATFORM-SSO | D12: ='Asset Register'!D2/'Asset Register'!E2 | E12: =D12*A12 | F12: ='Asset Register'!D2-E12
A13: 12 | B13: 2027-02 | C13: CAPEX-2026-PLATFORM-SSO | D13: ='Asset Register'!D2/'Asset Register'!E2 | E13: =D13*A13 | F13: ='Asset Register'!D2-E13
A14: 13 | B14: 2027-03 | C14: CAPEX-2026-PLATFORM-SSO | D14: ='Asset Register'!D2/'Asset Register'!E2 | E14: =D14*A14 | F14: ='Asset Register'!D2-E14
A15: 14 | B15: 2027-04 | C15: CAPEX-2026-PLATFORM-SSO | D15: ='Asset Register'!D2/'Asset Register'!E2 | E15: =D15*A15 | F15: ='Asset Register'!D2-E15
A16: 15 | B16: 2027-05 | C16: CAPEX-2026-PLATFORM-SSO | D16: ='Asset Register'!D2/'Asset Register'!E2 | E16: =D16*A16 | F16: ='Asset Register'!D2-E16
A17: 16 | B17: 2027-06 | C17: CAPEX-2026-PLATFORM-SSO | D17: ='Asset Register'!D2/'Asset Register'!E2 | E17: =D17*A17 | F17: ='Asset Register'!D2-E17
A18: 17 | B18: 2027-07 | C18: CAPEX-2026-PLATFORM-SSO | D18: ='Asset Register'!D2/'Asset Register'!E2 | E18: =D18*A18 | F18: ='Asset Register'!D2-E18
A19: 18 | B19: 2027-08 | C19: CAPEX-2026-PLATFORM-SSO | D19: ='Asset Register'!D2/'Asset Register'!E2 | E19: =D19*A19 | F19: ='Asset Register'!D2-E19
A20: 19 | B20: 2027-09 | C20: CAPEX-2026-PLATFORM-SSO | D20: ='Asset Register'!D2/'Asset Register'!E2 | E20: =D20*A20 | F20: ='Asset Register'!D2-E20
A21: 20 | B21: 2027-10 | C21: CAPEX-2026-PLATFORM-SSO | D21: ='Asset Register'!D2/'Asset Register'!E2 | E21: =D21*A21 | F21: ='Asset Register'!D2-E21
A22: 21 | B22: 2027-11 | C22: CAPEX-2026-PLATFORM-SSO | D22: ='Asset Register'!D2/'Asset Register'!E2 | E22: =D22*A22 | F22: ='Asset Register'!D2-E22
A23: 22 | B23: 2027-12 | C23: CAPEX-2026-PLATFORM-SSO | D23: ='Asset Register'!D2/'Asset Register'!E2 | E23: =D23*A23 | F23: ='Asset Register'!D2-E23
A24: 23 | B24: 2028-01 | C24: CAPEX-2026-PLATFORM-SSO | D24: ='Asset Register'!D2/'Asset Register'!E2 | E24: =D24*A24 | F24: ='Asset Register'!D2-E24
A25: 24 | B25: 2028-02 | C25: CAPEX-2026-PLATFORM-SSO | D25: ='Asset Register'!D2/'Asset Register'!E2 | E25: =D25*A25 | F25: ='Asset Register'!D2-E25
A26: 25 | B26: 2028-03 | C26: CAPEX-2026-PLATFORM-SSO | D26: ='Asset Register'!D2/'Asset Register'!E2 | E26: =D26*A26 | F26: ='Asset Register'!D2-E26
A27: 26 | B27: 2028-04 | C27: CAPEX-2026-PLATFORM-SSO | D27: ='Asset Register'!D2/'Asset Register'!E2 | E27: =D27*A27 | F27: ='Asset Register'!D2-E27
A28: 27 | B28: 2028-05 | C28: CAPEX-2026-PLATFORM-SSO | D28: ='Asset Register'!D2/'Asset Register'!E2 | E28: =D28*A28 | F28: ='Asset Register'!D2-E28
A29: 28 | B29: 2028-06 | C29: CAPEX-2026-PLATFORM-SSO | D29: ='Asset Register'!D2/'Asset Register'!E2 | E29: =D29*A29 | F29: ='Asset Register'!D2-E29
A30: 29 | B30: 2028-07 | C30: CAPEX-2026-PLATFORM-SSO | D30: ='Asset Register'!D2/'Asset Register'!E2 | E30: =D30*A30 | F30: ='Asset Register'!D2-E30
A31: 30 | B31: 2028-08 | C31: CAPEX-2026-PLATFORM-SSO | D31: ='Asset Register'!D2/'Asset Register'!E2 | E31: =D31*A31 | F31: ='Asset Register'!D2-E31
A32: 31 | B32: 2028-09 | C32: CAPEX-2026-PLATFORM-SSO | D32: ='Asset Register'!D2/'Asset Register'!E2 | E32: =D32*A32 | F32: ='Asset Register'!D2-E32
A33: 32 | B33: 2028-10 | C33: CAPEX-2026-PLATFORM-SSO | D33: ='Asset Register'!D2/'Asset Register'!E2 | E33: =D33*A33 | F33: ='Asset Register'!D2-E33
A34: 33 | B34: 2028-11 | C34: CAPEX-2026-PLATFORM-SSO | D34: ='Asset Register'!D2/'Asset Register'!E2 | E34: =D34*A34 | F34: ='Asset Register'!D2-E34
A35: 34 | B35: 2028-12 | C35: CAPEX-2026-PLATFORM-SSO | D35: ='Asset Register'!D2/'Asset Register'!E2 | E35: =D35*A35 | F35: ='Asset Register'!D2-E35
A36: 35 | B36: 2029-01 | C36: CAPEX-2026-PLATFORM-SSO | D36: ='Asset Register'!D2/'Asset Register'!E2 | E36: =D36*A36 | F36: ='Asset Register'!D2-E36
A37: 36 | B37: 2029-02 | C37: CAPEX-2026-PLATFORM-SSO | D37: ='Asset Register'!D2/'Asset Register'!E2 | E37: =D37*A37 | F37: ='Asset Register'!D2-E37
A39: Note: | B39: Copy rows 2-37 and adjust formulas/project codes for each additional project in the Asset Register.

Sheet Summary Dashboard
A1: Summary Dashboard
A3: Metric | B3: Value
A4: Total Capitalized (lifetime) | B4: =SUM('Asset Register'!D:D)
A5: Total Accumulated Amortization | B5: =SUM('Asset Register'!G:G)
A6: Total Net Book Value | B6: =SUM('Asset Register'!H:H)
A7: YTD Additions (current year — update range as needed) | B7: =SUMIF('Monthly Additions'!A:A,">=2026-01",'Monthly Additions'!C:C)
A9: Pivot hint: | B9: To convert into a pivot: select Asset Register and insert pivot.

Sheet Journal Entry Helper
A1: Date | B1: Account # | C1: Account Name | D1: Dr | E1: Cr | F1: Memo
A2: 2026-03-31 | B2: 1700 | C2: Capitalized Software (Asset) | D2: 180000 | F2: Mar 2026 capex per monthly report
A3: 2026-03-31 | B3: 6100 | C3: Salaries — Capitalized Offset | E3: 180000 | F3: Mar 2026 capex offset to engineering salaries
A4: 2026-03-31 | B4: 7400 | C4: Amortization Expense | D4: 5139 | F4: Mar 2026 amortization — CAPEX-2026-PLATFORM-SSO
A5: 2026-03-31 | B5: 1701 | C5: Accum. Amortization — Capitalized Software | E5: 5139 | F5: Mar 2026 amortization — CAPEX-2026-PLATFORM-SSO
A6: 2026-06-30 | B6: 7500 | C6: Impairment Loss | D6: 20000 | F6: Impair CAPEX-2026-RESIDENT-APP — project descoped
A7: 2026-06-30 | B7: 1700 | C7: Capitalized Software (Asset) | E7: 20000 | F7: Impair CAPEX-2026-RESIDENT-APP — project descoped
A8: 2029-03-31 | B8: 1701 | C8: Accum. Amortization — Capitalized Software | D8: 185000 | F8: Retire fully amortized CAPEX-2026-PLATFORM-SSO
A9: 2029-03-31 | B9: 1700 | C9: Capitalized Software (Asset) | E9: 185000 | F9: Retire fully amortized CAPEX-2026-PLATFORM-SSO
